timestream_cleaner/__init__.py
timestream_cleaner/timestream_cleaner.py
timestream_cleaner-0.1.0.dist-info/METADATA
timestream_cleaner-0.1.0.dist-info/WHEEL
timestream_cleaner-0.1.0.dist-info/entry_points.txt
timestream_cleaner-0.1.0.dist-info/licenses/LICENSE
timestream_cleaner-0.1.0.dist-info/RECORD
