Metadata-Version: 2.4
Name: timestream-cleaner
Version: 0.1.0
Summary: Amazon Timestream Database Table Cleanup Tool
Project-URL: Homepage, https://juliobs.com/project/timestream-cleaner
Project-URL: Documentation, https://github.com/jbsilva/timestream-cleaner#readme
Project-URL: Repository, https://github.com/jbsilva/timestream-cleaner
Project-URL: CI, https://github.com/jbsilva/timestream-cleaner/actions
Project-URL: Issues, https://github.com/jbsilva/timestream-cleaner/issues
Author-email: Julio Batista Silva <python@juliobs.com>
License: MIT
License-File: LICENSE
Keywords: aws,cleaner,cleanup,cli,database,timestream,tool
Classifier: Development Status :: 4 - Beta
Classifier: Environment :: Console
Classifier: Intended Audience :: Developers
Classifier: Intended Audience :: System Administrators
Classifier: License :: OSI Approved :: MIT License
Classifier: Operating System :: OS Independent
Classifier: Programming Language :: Python :: 3
Classifier: Programming Language :: Python :: 3 :: Only
Classifier: Programming Language :: Python :: 3.12
Classifier: Programming Language :: Python :: 3.13
Classifier: Programming Language :: Python :: 3.14
Classifier: Topic :: Database
Classifier: Topic :: Internet
Classifier: Topic :: Software Development :: Libraries :: Python Modules
Classifier: Topic :: System :: Systems Administration
Classifier: Topic :: Utilities
Requires-Python: >=3.12
Requires-Dist: boto3-stubs[timestream-write]>=1.36.11
Requires-Dist: boto3>=1.36.11
Requires-Dist: loguru>=0.7.3
Requires-Dist: typer>=0.15.1
